MANIFEST.in
README.txt
setup.py
docs/HISTORY.txt
docs/INSTALL.txt
docs/LICENSE.txt
megrok/__init__.py
megrok.z3cform.crud.egg-info/PKG-INFO
megrok.z3cform.crud.egg-info/SOURCES.txt
megrok.z3cform.crud.egg-info/dependency_links.txt
megrok.z3cform.crud.egg-info/namespace_packages.txt
megrok.z3cform.crud.egg-info/not-zip-safe
megrok.z3cform.crud.egg-info/requires.txt
megrok.z3cform.crud.egg-info/top_level.txt
megrok/z3cform/__init__.py
megrok/z3cform/crud/__init__.py
megrok/z3cform/crud/crud.py
megrok/z3cform/crud/widget.py
megrok/z3cform/crud/tests/__init__.py
megrok/z3cform/crud/tests/test_all.py