Metadata-Version: 1.0
Name: megrok.z3cform.crud
Version: 0.1
Summary: Crud forms for Grok, uusing z3c.form
Home-page: http://pypi.python.org/pypi/megrok.z3cform.crud
Author: Danilo G. Botelho
Author-email: danilogbotelho@yahoo.com
License: GPL
Keywords: Grok CRUD z3c.form
Platform: UNKNOWN
Classifier: Framework :: Zope3
Classifier: Programming Language :: Python
